Piscord/__init__.py
Piscord_Astremy_Test-1.0.0.dist-info/LICENSE
Piscord_Astremy_Test-1.0.0.dist-info/METADATA
Piscord_Astremy_Test-1.0.0.dist-info/WHEEL
Piscord_Astremy_Test-1.0.0.dist-info/top_level.txt
Piscord_Astremy_Test-1.0.0.dist-info/RECORD
