Metadata-Version: 2.1
Name: Piscord-Astremy-Test
Version: 1.0.0
Summary: Piscord is a python framework to communicate with the Discord api.
Home-page: https://github.com/Astremy/Piscord
Author: Astremy
Author-email: 
License: UNKNOWN
Platform: UNKNOWN
Classifier: Programming Language :: Python :: 3
Classifier: License :: OSI Approved :: MIT License
Classifier: Operating System :: OS Independent
Requires-Python: >=3.6
